cyclonedx/__init__.py
cyclonedx/_internal/__init__.py
cyclonedx/_internal/bom_ref.py
cyclonedx/_internal/compare.py
cyclonedx/_internal/hash.py
cyclonedx/_internal/time.py
cyclonedx/builder/__init__.py
cyclonedx/builder/this.py
cyclonedx/exception/__init__.py
cyclonedx/exception/factory.py
cyclonedx/exception/model.py
cyclonedx/exception/output.py
cyclonedx/exception/serialization.py
cyclonedx/factory/__init__.py
cyclonedx/factory/license.py
cyclonedx/model/__init__.py
cyclonedx/model/bom.py
cyclonedx/model/bom_ref.py
cyclonedx/model/component.py
cyclonedx/model/component_evidence.py
cyclonedx/model/contact.py
cyclonedx/model/crypto.py
cyclonedx/model/definition.py
cyclonedx/model/dependency.py
cyclonedx/model/impact_analysis.py
cyclonedx/model/issue.py
cyclonedx/model/license.py
cyclonedx/model/lifecycle.py
cyclonedx/model/release_note.py
cyclonedx/model/service.py
cyclonedx/model/tool.py
cyclonedx/model/vulnerability.py
cyclonedx/output/__init__.py
cyclonedx/output/json.py
cyclonedx/output/xml.py
cyclonedx/py.typed
cyclonedx/schema/__init__.py
cyclonedx/schema/_res/README.md
cyclonedx/schema/_res/__init__.py
cyclonedx/schema/_res/bom-1.0.SNAPSHOT.xsd
cyclonedx/schema/_res/bom-1.1.SNAPSHOT.xsd
cyclonedx/schema/_res/bom-1.2-strict.SNAPSHOT.schema.json
cyclonedx/schema/_res/bom-1.2.SNAPSHOT.schema.json
cyclonedx/schema/_res/bom-1.2.SNAPSHOT.xsd
cyclonedx/schema/_res/bom-1.3-strict.SNAPSHOT.schema.json
cyclonedx/schema/_res/bom-1.3.SNAPSHOT.schema.json
cyclonedx/schema/_res/bom-1.3.SNAPSHOT.xsd
cyclonedx/schema/_res/bom-1.4.SNAPSHOT.schema.json
cyclonedx/schema/_res/bom-1.4.SNAPSHOT.xsd
cyclonedx/schema/_res/bom-1.5.SNAPSHOT.schema.json
cyclonedx/schema/_res/bom-1.5.SNAPSHOT.xsd
cyclonedx/schema/_res/bom-1.6.SNAPSHOT.schema.json
cyclonedx/schema/_res/bom-1.6.SNAPSHOT.xsd
cyclonedx/schema/_res/bom-1.7.SNAPSHOT.schema.json
cyclonedx/schema/_res/bom-1.7.SNAPSHOT.xsd
cyclonedx/schema/_res/cryptography-defs.SNAPSHOT.schema.json
cyclonedx_python_lib-11.4.0.dist-info/METADATA
cyclonedx_python_lib-11.4.0.dist-info/WHEEL
cyclonedx_python_lib-11.4.0.dist-info/licenses/LICENSE
cyclonedx_python_lib-11.4.0.dist-info/licenses/NOTICE
cyclonedx_python_lib-11.4.0.dist-info/RECORD
