Metadata-Version: 2.4
Name: cyclonedx-python-lib
Version: 11.4.0
Summary: Python library for CycloneDX
License: Apache-2.0
License-File: LICENSE
License-File: NOTICE
Keywords: CycloneDX,library,OWASP,SCA,Software Bill of Materials,Bill of Materials,BOM,SBOM,VEX,VDR,OBOM,MBOM,SaaSBOM,SPDX,PackageURL,PURL
Author: Paul Horton
Author-email: phorton@sonatype.com
Maintainer: Jan Kowalleck
Maintainer-email: jan.kowalleck@gmail.com
Requires-Python: >=3.9,<4.0
Classifier: Development Status :: 5 - Production/Stable
Classifier: Intended Audience :: Developers
Classifier: Intended Audience :: Information Technology
Classifier: Intended Audience :: Legal Industry
Classifier: Intended Audience :: System Administrators
Classifier: License :: OSI Approved :: Apache Software License
Classifier: Programming Language :: Python :: 3
Classifier: Programming Language :: Python :: 3.9
Classifier: Programming Language :: Python :: 3.10
Classifier: Programming Language :: Python :: 3.11
Classifier: Programming Language :: Python :: 3.12
Classifier: Programming Language :: Python :: 3.13
Classifier: Programming Language :: Python :: 3.14
Classifier: Topic :: Security
Classifier: Topic :: Software Development
Classifier: Topic :: System :: Software Distribution
Classifier: Typing :: Typed
Provides-Extra: json-validation
Provides-Extra: validation
Provides-Extra: xml-validation
Requires-Dist: jsonschema[format-nongpl] (>=4.25,<5.0) ; extra == "validation" or extra == "json-validation"
Requires-Dist: license-expression (>=30,<31)
Requires-Dist: lxml (>=4,<7) ; extra == "validation" or extra == "xml-validation"
Requires-Dist: packageurl-python (>=0.11,<2)
Requires-Dist: py-serializable (>=2.1.0,<3.0.0)
Requires-Dist: referencing (>=0.28.4) ; extra == "validation" or extra == "json-validation"
Requires-Dist: sortedcontainers (>=2.4.0,<3.0.0)
Requires-Dist: typing_extensions (>=4.6,<5.0) ; python_version < "3.13"
Project-URL: Bug Tracker, https://github.com/CycloneDX/cyclonedx-python-lib/issues
Project-URL: Changelog, https://github.com/CycloneDX/cyclonedx-python-lib/releases
Project-URL: Documentation, https://cyclonedx-python-library.readthedocs.io/
Project-URL: Funding, https://owasp.org/donate/?reponame=www-project-cyclonedx&title=OWASP+CycloneDX
Project-URL: Homepage, https://github.com/CycloneDX/cyclonedx-python-lib/#readme
Project-URL: Repository, https://github.com/CycloneDX/cyclonedx-python-lib
